browndog/__init__.py
browndog/bd.py
browndog-0.5.0.dist-info/DESCRIPTION.rst
browndog-0.5.0.dist-info/METADATA
browndog-0.5.0.dist-info/RECORD
browndog-0.5.0.dist-info/WHEEL
browndog-0.5.0.dist-info/metadata.json
browndog-0.5.0.dist-info/top_level.txt
